{
  "fecha": "2026-03-17T08:06:33.108Z",
  "tablas": {
    "clientes": {
      "registros": 106,
      "ok": true
    },
    "rrhh": {
      "registros": 38,
      "ok": true
    },
    "ddjj_state": {
      "registros": 87,
      "ok": true
    },
    "facturas": {
      "registros": 48,
      "ok": true
    },
    "at2026_facturas": {
      "registros": 0,
      "ok": true
    },
    "at2026_abonos": {
      "registros": 0,
      "ok": true
    },
    "cartola_movimientos": {
      "registros": 227,
      "ok": true
    },
    "cartola_cuentas": {
      "registros": 1,
      "ok": true
    },
    "conciliaciones": {
      "registros": 0,
      "ok": true
    },
    "activity_log": {
      "registros": 1042,
      "ok": true
    },
    "personal": {
      "registros": 5,
      "ok": true
    },
    "notificaciones": {
      "registros": 765,
      "ok": true
    }
  },
  "total_registros": 2319,
  "errores": []
}